reels_downloader/__init__.py
reels_downloader/common/__init__.py
reels_downloader/common/model/ReelAuthor.py
reels_downloader/common/model/ReelModel.py
reels_downloader/common/model/ReelPreview.py
reels_downloader/common/model/ReelVideo.py
reels_downloader/common/model/__init__.py
reels_downloader/main/MediaInfo.py
reels_downloader/main/Reels.py
reels_downloader/main/__init__.py
downloader_for_reels-0.1.7.dist-info/METADATA
downloader_for_reels-0.1.7.dist-info/WHEEL
downloader_for_reels-0.1.7.dist-info/RECORD
