Metadata-Version: 2.1
Name: downloader-for-reels
Version: 0.1.7
Summary: Reels Download Module
Home-page: https://gitlab.com/bitt_moe/instagram/reels_downloader
Author: Николай Витальевич Никоноров
Author-email: nnv@bitt.moe
Requires-Python: >=3.10,<4.0
Classifier: Programming Language :: Python :: 3
Classifier: Programming Language :: Python :: 3.10
Classifier: Programming Language :: Python :: 3.11
Requires-Dist: aiohttp (==3.8.3)
Requires-Dist: aiosignal (==1.3.1)
Requires-Dist: async-timeout (==4.0.2)
Requires-Dist: attrs (==22.2.0)
Requires-Dist: beautifulsoup4 (==4.11.2)
Requires-Dist: charset-normalizer (==2.1.1)
Requires-Dist: frozenlist (==1.3.3)
Requires-Dist: idna (==3.4)
Requires-Dist: multidict (==6.0.4)
Requires-Dist: soupsieve (==2.3.2.post1)
Requires-Dist: yarl (==1.8.2)
Project-URL: Repository, https://gitlab.com/bitt_moe/instagram/reels_downloader
